__init__.py
__main__.py
flashcards.py
screen_utils.py
test_flashcards.py
flashcards_json-1.0.9.dist-info/METADATA
flashcards_json-1.0.9.dist-info/WHEEL
flashcards_json-1.0.9.dist-info/licenses/LICENSE
flashcards_json-1.0.9.dist-info/RECORD
