Metadata-Version: 2.3
Name: flashcards-json
Version: 1.0.9
Summary: A configurable learning tool
Project-URL: Homepage, https://github.com/wrycoder/python-projects/tree/master/flashcards
Project-URL: Issues, https://github.com/wrycoder/python-projects/issues
Author-email: Michael Toulouse <deryankee@gmail.com>
License-File: LICENSE
Classifier: Environment :: Console :: Curses
Classifier: Intended Audience :: Education
Classifier: License :: OSI Approved :: MIT License
Classifier: Operating System :: OS Independent
Classifier: Programming Language :: Python :: 3
Requires-Python: >=3.12
